dinkydicom/__init__.py
dinkydicom/dinkydicom.py
dinkydicom-1.1.0.dist-info/LICENSE
dinkydicom-1.1.0.dist-info/METADATA
dinkydicom-1.1.0.dist-info/WHEEL
dinkydicom-1.1.0.dist-info/entry_points.txt
dinkydicom-1.1.0.dist-info/RECORD
