Metadata-Version: 2.3
Name: dinkydicom
Version: 1.1.0
Summary: viewer for enhanced MR dicoms with mosaic options
License: MIT
Author: Jolinda Smith
Author-email: jolinda@uoregon.edu
Requires-Python: >=3.10
Classifier: License :: OSI Approved :: MIT License
Classifier: Programming Language :: Python :: 3
Classifier: Programming Language :: Python :: 3.10
Classifier: Programming Language :: Python :: 3.11
Classifier: Programming Language :: Python :: 3.12
Classifier: Programming Language :: Python :: 3.13
Requires-Dist: freesimplegui
Requires-Dist: matplotlib (>=3.6)
Requires-Dist: numpy (>=1.23)
Requires-Dist: pydicom (>=2.3)
